perfcat/__init__.py
perfcat/__main__.py
perfcat/adb/AdbWinApi.dll
perfcat/adb/AdbWinUsbApi.dll
perfcat/adb/adb.exe
perfcat/components/__init__.py
perfcat/components/layout.py
perfcat/components/monitors/__init__.py
perfcat/components/monitors/battery_monitor.py
perfcat/components/monitors/cpu_monitor.py
perfcat/components/monitors/fps_monitor.py
perfcat/components/monitors/memery_monitor.py
perfcat/components/monitors/temperature_monitor.py
perfcat/components/monitors/traffic_monitor.py
perfcat/components/profiler.py
perfcat/config.py
perfcat/logger.py
perfcat/media/__init__.py
perfcat/pages/__init__.py
perfcat/pages/android_profiler/__init__.py
perfcat/pages/home/__init__.py
perfcat/pages/home/home.py
perfcat/pages/report/__init__.py
perfcat/services/__init__.py
perfcat/services/android_profiler_service.py
perfcat/services/record_service.py
perfcat/static/__init__.py
perfcat/static/icon.png
perfcat/static/js/html2canvas.min.js
perfcat/utils/__init__.py
performance_catcher-2.1.0.dist-info/LICENSE
performance_catcher-2.1.0.dist-info/METADATA
performance_catcher-2.1.0.dist-info/WHEEL
performance_catcher-2.1.0.dist-info/entry_points.txt
performance_catcher-2.1.0.dist-info/RECORD
