Metadata-Version: 2.3
Name: performance-catcher
Version: 2.1.0
Summary: Android Performance Toolkit
License: MIT
Author: kaluluosi111
Author-email: kaluluosi@gmail.com
Requires-Python: >=3.11,<3.14
Classifier: License :: OSI Approved :: MIT License
Classifier: Programming Language :: Python :: 3
Classifier: Programming Language :: Python :: 3.11
Classifier: Programming Language :: Python :: 3.12
Classifier: Programming Language :: Python :: 3.13
Requires-Dist: async-adbc (==1.1.2)
Requires-Dist: html2image (>=2.0.7,<3.0.0)
Requires-Dist: nicegui (>=2.20.0,<3.0.0)
Requires-Dist: pydantic (>=2.11.7,<3.0.0)
Requires-Dist: pydantic-settings (>=2.9.1,<3.0.0)
Requires-Dist: pywebview (>=5.4,<6.0)
Requires-Dist: reactivex (>=4.0.4,<5.0.0)
Requires-Dist: toml (>=0.10.2,<0.11.0)
Project-URL: Repository, https://github.com/kaluluosi/performance-catcher
